webdriver_hj3415/__init__.py
webdriver_hj3415/drivers.py
webdriver_hj3415-2.0.0.dist-info/WHEEL
webdriver_hj3415-2.0.0.dist-info/METADATA
webdriver_hj3415-2.0.0.dist-info/RECORD
