Metadata-Version: 2.3
Name: webdriver-hj3415
Version: 2.0.0
Summary: The webdriver functions for hj3415
Author-email: Hyungjin Kim <hj3415@gmail.com>
Classifier: License :: OSI Approved :: MIT License
Requires-Dist: selenium>=4.27.1
Requires-Dist: webdriver-manager>=4.0.2
Requires-Dist: utils_hj3415>=3.0.13
Project-URL: Home, https://www.hyungjin.kr
